{
  "id": "2025-2026:3-5:2026-03-21",
  "year": "2025-2026",
  "division": "3-5",
  "dateString": "2026-03-21",
  "puzzle": {
    "grid": [
      [
        null,
        null,
        null,
        null,
        null,
        null,
        null,
        null,
        null,
        null,
        null,
        null,
        null,
        null,
        null,
        null,
        null
      ],
      [
        null,
        null,
        null,
        null,
        null,
        "H",
        null,
        null,
        "B",
        "U",
        "T",
        "T",
        "E",
        "R",
        "N",
        "U",
        "T"
      ],
      [
        null,
        null,
        null,
        null,
        null,
        "O",
        null,
        null,
        "L",
        null,
        null,
        null,
        null,
        null,
        null,
        null,
        null
      ],
      [
        null,
        null,
        null,
        "M",
        "A",
        "R",
        "T",
        "H",
        "A",
        null,
        null,
        null,
        "G",
        null,
        null,
        null,
        null
      ],
      [
        null,
        null,
        null,
        null,
        null,
        "S",
        null,
        null,
        "C",
        "A",
        "M",
        "E",
        "R",
        "O",
        "N",
        null,
        null
      ],
      [
        null,
        null,
        "B",
        null,
        null,
        "E",
        null,
        null,
        "K",
        null,
        null,
        null,
        "A",
        null,
        null,
        null,
        null
      ],
      [
        null,
        "W",
        "O",
        "R",
        "D",
        "S",
        null,
        null,
        null,
        null,
        null,
        null,
        "N",
        null,
        null,
        null,
        null
      ],
      [
        null,
        null,
        "D",
        null,
        null,
        null,
        "C",
        "O",
        "M",
        "M",
        "A",
        "N",
        "D",
        "E",
        "R",
        null,
        null
      ],
      [
        "T",
        "W",
        "E",
        "L",
        "V",
        "E",
        null,
        null,
        null,
        null,
        null,
        null,
        "M",
        null,
        null,
        null,
        null
      ],
      [
        null,
        null,
        "G",
        null,
        null,
        null,
        null,
        null,
        "S",
        "U",
        "N",
        "D",
        "A",
        "Y",
        null,
        null,
        null
      ],
      [
        null,
        "P",
        "A",
        "N",
        "E",
        "L",
        null,
        "L",
        null,
        null,
        null,
        null,
        null,
        null,
        null,
        null,
        null
      ],
      [
        null,
        null,
        null,
        null,
        "G",
        null,
        null,
        "I",
        null,
        "R",
        null,
        null,
        null,
        null,
        null,
        null,
        null
      ],
      [
        null,
        "K",
        "I",
        "N",
        "G",
        "F",
        "I",
        "S",
        "H",
        "E",
        "R",
        null,
        null,
        "F",
        null,
        null,
        null
      ],
      [
        null,
        null,
        null,
        null,
        "S",
        null,
        null,
        "E",
        null,
        "A",
        null,
        "C",
        null,
        "O",
        null,
        "J",
        null
      ],
      [
        null,
        null,
        null,
        null,
        null,
        null,
        null,
        null,
        null,
        "D",
        "R",
        "A",
        "C",
        "U",
        "L",
        "A",
        null
      ],
      [
        null,
        null,
        null,
        null,
        null,
        null,
        null,
        null,
        null,
        null,
        null,
        "T",
        null,
        "R",
        null,
        "Y",
        null
      ],
      [
        null,
        null,
        null,
        null,
        null,
        null,
        null,
        null,
        null,
        null,
        null,
        null,
        null,
        null,
        null,
        null,
        null
      ]
    ],
    "clues": [
      {
        "id": "1-across",
        "number": 1,
        "direction": "across",
        "text": "What blue bird with a crest and sharp beak does Brian see sitting on a limb by the lake?",
        "answer": "KINGFISHER",
        "startRow": 12,
        "startCol": 1,
        "length": 10,
        "bookKey": "hatchet",
        "bookTitle": "Hatchet",
        "page": 74
      },
      {
        "id": "2-down",
        "number": 2,
        "direction": "down",
        "text": "by what other name do characters call the corner store?",
        "answer": "BODEGA",
        "startRow": 5,
        "startCol": 2,
        "length": 6,
        "bookKey": "the-secret-garden-on-81st-street",
        "bookTitle": "The Secret Garden on 81st Street",
        "page": 23
      },
      {
        "id": "3-down",
        "number": 3,
        "direction": "down",
        "text": "What did kids throw at the families front door?",
        "answer": "EGGS",
        "startRow": 10,
        "startCol": 4,
        "length": 4,
        "bookKey": "inside-out-and-back-again",
        "bookTitle": "Inside Out and Back Again",
        "page": 162
      },
      {
        "id": "4-down",
        "number": 4,
        "direction": "down",
        "text": "What is 1975 the year of?",
        "answer": "CAT",
        "startRow": 13,
        "startCol": 11,
        "length": 3,
        "bookKey": "inside-out-and-back-again",
        "bookTitle": "Inside Out and Back Again",
        "page": 1
      },
      {
        "id": "5-down",
        "number": 5,
        "direction": "down",
        "text": "What person died two weeks before a wedding?",
        "answer": "LISE",
        "startRow": 10,
        "startCol": 7,
        "length": 4,
        "bookKey": "number-the-stars",
        "bookTitle": "Number the Stars",
        "page": 16
      },
      {
        "id": "6-across",
        "number": 6,
        "direction": "across",
        "text": "how old does Emily tell Shona she is?",
        "answer": "TWELVE",
        "startRow": 8,
        "startCol": 0,
        "length": 6,
        "bookKey": "the-tail-of-emily-windsnap",
        "bookTitle": "The Tail of Emily Windsnap",
        "page": 34
      },
      {
        "id": "7-down",
        "number": 7,
        "direction": "down",
        "text": "How many humans live in the house?",
        "answer": "FOUR",
        "startRow": 12,
        "startCol": 13,
        "length": 4,
        "bookKey": "the-remarkable-rescue-at-milkweed-meadow",
        "bookTitle": "The Remarkable Rescue at Milkweed Meadow",
        "page": 159
      },
      {
        "id": "8-across",
        "number": 8,
        "direction": "across",
        "text": "what is the rabbit narrator's name?",
        "answer": "BUTTERNUT",
        "startRow": 1,
        "startCol": 8,
        "length": 9,
        "bookKey": "the-remarkable-rescue-at-milkweed-meadow",
        "bookTitle": "The Remarkable Rescue at Milkweed Meadow",
        "page": 8
      },
      {
        "id": "8-down",
        "number": 8,
        "direction": "down",
        "text": "What color does Ellen offer to have her father dye Kirsti\"s new shoes?",
        "answer": "BLACK",
        "startRow": 1,
        "startCol": 8,
        "length": 5,
        "bookKey": "number-the-stars",
        "bookTitle": "Number the Stars",
        "page": 29
      },
      {
        "id": "9-across",
        "number": 9,
        "direction": "across",
        "text": "On the boat, whose bathroom is Ha allowed to use that she describes as white and clean?",
        "answer": "COMMANDER",
        "startRow": 7,
        "startCol": 6,
        "length": 9,
        "bookKey": "inside-out-and-back-again",
        "bookTitle": "Inside Out and Back Again",
        "page": 74
      },
      {
        "id": "10-across",
        "number": 10,
        "direction": "across",
        "text": "What is the name of the character who is charged with watching Mary while her uncle is away?",
        "answer": "MARTHA",
        "startRow": 3,
        "startCol": 3,
        "length": 6,
        "bookKey": "the-secret-garden-on-81st-street",
        "bookTitle": "The Secret Garden on 81st Street",
        "page": 18
      },
      {
        "id": "11-across",
        "number": 11,
        "direction": "across",
        "text": "According to Morimer he had a lot of feelings, what he didn't have were a lot of \"what'?",
        "answer": "WORDS",
        "startRow": 6,
        "startCol": 1,
        "length": 5,
        "bookKey": "the-lost-library",
        "bookTitle": "The Lost Library",
        "page": 1
      },
      {
        "id": "12-across",
        "number": 12,
        "direction": "across",
        "text": "Lina and Doon think they're looking for a key behind a small steel pan, but what word is \"pan\" actually short for in the Instructions?",
        "answer": "PANEL",
        "startRow": 10,
        "startCol": 1,
        "length": 5,
        "bookKey": "city-of-ember",
        "bookTitle": "City of Ember",
        "page": 185
      },
      {
        "id": "13-across",
        "number": 13,
        "direction": "across",
        "text": "On which day of the week does Emily's mom always sleep in?",
        "answer": "SUNDAY",
        "startRow": 9,
        "startCol": 8,
        "length": 6,
        "bookKey": "the-tail-of-emily-windsnap",
        "bookTitle": "The Tail of Emily Windsnap",
        "page": 113
      },
      {
        "id": "14-down",
        "number": 14,
        "direction": "down",
        "text": "who does Langston wish they would not have left in Alabama?",
        "answer": "GRANDMA",
        "startRow": 3,
        "startCol": 12,
        "length": 7,
        "bookKey": "finding-langston",
        "bookTitle": "Finding Langston",
        "page": 24
      },
      {
        "id": "15-across",
        "number": 15,
        "direction": "across",
        "text": "Who does Avery plan an \"intragalactic hangout\" with?",
        "answer": "CAMERON",
        "startRow": 4,
        "startCol": 8,
        "length": 7,
        "bookKey": "squished",
        "bookTitle": "Squished",
        "page": 158
      },
      {
        "id": "16-down",
        "number": 16,
        "direction": "down",
        "text": "what do Celia and Nick ride when they try to find a girl in trouble in the middle of the night?",
        "answer": "HORSES",
        "startRow": 1,
        "startCol": 5,
        "length": 6,
        "bookKey": "just-like-click",
        "bookTitle": "Just Like Click",
        "page": 135
      },
      {
        "id": "17-down",
        "number": 17,
        "direction": "down",
        "text": "who first has the idea of making a reality TV show of the Falloon family?",
        "answer": "JAY",
        "startRow": 13,
        "startCol": 15,
        "length": 3,
        "bookKey": "the-million-dollar-race",
        "bookTitle": "The Million Dollar Race",
        "page": 7
      },
      {
        "id": "18-down",
        "number": 18,
        "direction": "down",
        "text": "what is the answer to the final clue \"Once you learn how to do this, you will be forever free.\"?",
        "answer": "READ",
        "startRow": 11,
        "startCol": 9,
        "length": 4,
        "bookKey": "escape-from-mr-lemoncellos-library",
        "bookTitle": "Escape from Mr. Lemoncello's Library",
        "page": 285
      },
      {
        "id": "19-across",
        "number": 19,
        "direction": "across",
        "text": "What kind of dolls does Mr. Falloon make?",
        "answer": "DRACULA",
        "startRow": 14,
        "startCol": 9,
        "length": 7,
        "bookKey": "the-million-dollar-race",
        "bookTitle": "The Million Dollar Race",
        "page": 62
      }
    ],
    "rows": 17,
    "cols": 17,
    "cellNumbers": {
      "12,1": 1,
      "5,2": 2,
      "10,4": 3,
      "13,11": 4,
      "10,7": 5,
      "8,0": 6,
      "12,13": 7,
      "1,8": 8,
      "7,6": 9,
      "3,3": 10,
      "6,1": 11,
      "10,1": 12,
      "9,8": 13,
      "3,12": 14,
      "4,8": 15,
      "1,5": 16,
      "13,15": 17,
      "11,9": 18,
      "14,9": 19
    }
  },
  "generatedAt": 1772202773852,
  "clueCount": 20
}